swift_comet_pipeline/__init__.py
swift_comet_pipeline/aperture/__init__.py
swift_comet_pipeline/aperture/aperture_count_rate.py
swift_comet_pipeline/aperture/concentric_annuli.py
swift_comet_pipeline/aperture/plateau_detect.py
swift_comet_pipeline/aperture/plateau_distribution_seaborn.py
swift_comet_pipeline/aperture/plateau_serialize.py
swift_comet_pipeline/aperture/q_vs_aperture_kde_seaborn.py
swift_comet_pipeline/aperture/q_vs_aperture_radius.py
swift_comet_pipeline/aperture/q_vs_aperture_radius_matplotlib.py
swift_comet_pipeline/aperture/q_vs_aperture_radius_seaborn.py
swift_comet_pipeline/background/__init__.py
swift_comet_pipeline/background/determine_background.py
swift_comet_pipeline/background/methods/__init__.py
swift_comet_pipeline/background/methods/bg_method_aperture.py
swift_comet_pipeline/background/methods/bg_method_aperture_ensemble.py
swift_comet_pipeline/background/methods/bg_method_gui_manual_aperture.py
swift_comet_pipeline/comet/__init__.py
swift_comet_pipeline/comet/calculate_column_density.py
swift_comet_pipeline/comet/comet_center.py
swift_comet_pipeline/comet/comet_center_finding.py
swift_comet_pipeline/comet/comet_profile_fitting.py
swift_comet_pipeline/comet/comet_radius.py
swift_comet_pipeline/comet/countrate_profile_to_surface_brightness.py
swift_comet_pipeline/comet/extract_comet_radial_profile.py
swift_comet_pipeline/comet/subtract_comet_profiles.py
swift_comet_pipeline/dust/__init__.py
swift_comet_pipeline/dust/afrho.py
swift_comet_pipeline/dust/beta_parameter.py
swift_comet_pipeline/dust/dust_limits.py
swift_comet_pipeline/dust/dust_redness_prior.py
swift_comet_pipeline/dust/halley_marcus.py
swift_comet_pipeline/dust/reddening_correction.py
swift_comet_pipeline/fluorescence/__init__.py
swift_comet_pipeline/fluorescence/hydroxyl_gfactor.py
swift_comet_pipeline/image_manipulation/__init__.py
swift_comet_pipeline/image_manipulation/compositing.py
swift_comet_pipeline/image_manipulation/event_mode_downsample.py
swift_comet_pipeline-0.2.3.dist-info/LICENSE
swift_comet_pipeline-0.2.3.dist-info/METADATA
swift_comet_pipeline-0.2.3.dist-info/WHEEL
swift_comet_pipeline-0.2.3.dist-info/entry_points.txt
swift_comet_pipeline-0.2.3.dist-info/RECORD
