Metadata-Version: 2.1
Name: swift_comet_pipeline
Version: 0.2.3
Summary: Data reduction pipeline for determining water production rates from the Swift telescope's UVOT images
License: LICENSE
Author: Shawn Oset
Requires-Python: >=3.11,<3.13
Classifier: License :: Other/Proprietary License
Classifier: Programming Language :: Python :: 3
Classifier: Programming Language :: Python :: 3.11
Classifier: Programming Language :: Python :: 3.12
Requires-Dist: astropy (>=5.3.4)
Requires-Dist: astroquery (>=0.4.6)
Requires-Dist: comet-ice-sublimation (>=0.0.1,<0.0.2)
Requires-Dist: icecream (>=2.1.3,<3.0.0)
Requires-Dist: jupyterlab (>=4.4.0,<5.0.0)
Requires-Dist: matplotlib (>=3.8.0)
Requires-Dist: numpy (>=1.26.1)
Requires-Dist: pandas (>=2.1.1)
Requires-Dist: photutils (>=1.9.0)
Requires-Dist: pyabel (>=0.9.0,<0.10.0)
Requires-Dist: pyarrow (>=13.0.0)
Requires-Dist: pyvectorial-au (>=1.1.1,<2.0.0)
Requires-Dist: questionary (>=2.0.1,<3.0.0)
Requires-Dist: regions (>=0.10,<0.11)
Requires-Dist: rich (>=13.6.0,<14.0.0)
Requires-Dist: sbpy (>=0.4.0,<0.5.0)
Requires-Dist: scikit-image (>=0.24.0,<0.25.0)
Requires-Dist: scikit-learn (>=1.5.2,<2.0.0)
Requires-Dist: scipy (>=1.11.3)
Requires-Dist: seaborn (>=0.13.2,<0.14.0)
Requires-Dist: tqdm (>=4.66.1)
